pytaskmaster/__init__.py
pytaskmaster/version.py
pytaskmaster-1.1.3.data/scripts/master
pytaskmaster-1.1.3.dist-info/DESCRIPTION.rst
pytaskmaster-1.1.3.dist-info/METADATA
pytaskmaster-1.1.3.dist-info/RECORD
pytaskmaster-1.1.3.dist-info/WHEEL
pytaskmaster-1.1.3.dist-info/metadata.json
pytaskmaster-1.1.3.dist-info/top_level.txt
