Metadata-Version: 2.0
Name: pytaskmaster
Version: 1.1.3
Summary: Python library for create build scripts
Home-page: https://github.com/Plambir/pytaskmaster
Author: Alexander Prusov
Author-email: alexprusov@gmail.com
License: MIT
Keywords: pytaskmaster buildtools development
Platform: UNKNOWN
Classifier: Development Status :: 5 - Production/Stable
Classifier: Intended Audience :: Developers
Classifier: Topic :: Software Development :: Build Tools
Classifier: License :: OSI Approved :: MIT License
Classifier: Programming Language :: Python :: 2
Classifier: Programming Language :: Python :: 2.6
Classifier: Programming Language :: Python :: 2.7
Classifier: Programming Language :: Python :: 3
Classifier: Programming Language :: Python :: 3.2
Classifier: Programming Language :: Python :: 3.3
Classifier: Programming Language :: Python :: 3.4
Provides-Extra: dev
Requires-Dist: check-manifest; extra == 'dev'
